LICENSE
MANIFEST.in
README.md
requirements.txt
setup.py
pxmeter/__init__.py
pxmeter/calc_metric.py
pxmeter/cli.py
pxmeter/constants.py
pxmeter/eval.py
pxmeter/mapping.py
pxmeter/utils.py
pxmeter.egg-info/PKG-INFO
pxmeter.egg-info/SOURCES.txt
pxmeter.egg-info/dependency_links.txt
pxmeter.egg-info/entry_points.txt
pxmeter.egg-info/requires.txt
pxmeter.egg-info/top_level.txt
pxmeter/configs/__init__.py
pxmeter/configs/data_config.py
pxmeter/configs/run_config.py
pxmeter/data/__init__.py
pxmeter/data/ccd.py
pxmeter/data/parser.py
pxmeter/data/struct.py
pxmeter/data/utils.py
pxmeter/data/writer.py
pxmeter/metrics/__init__.py
pxmeter/metrics/clashes.py
pxmeter/metrics/lddt_metrics.py
pxmeter/metrics/rmsd.py
pxmeter/metrics/rmsd_metrics.py
pxmeter/permutation/__init__.py
pxmeter/permutation/atom.py
pxmeter/permutation/chain.py
pxmeter/permutation/residue.py