Metadata-Version: 2.4
Name: pxmeter
Version: 0.1.6
Summary: PXMeter is a comprehensive toolkit for evaluating the quality of         structures generated by biomolecular structure prediction models.
Author: Bytedance Inc.
Author-email: ai4s-bio@bytedance.com
License: Apache 2.0 License
Platform: manylinux1
Requires-Python: >=3.11
License-File: LICENSE
Requires-Dist: biotite>=1.2.0
Requires-Dist: dockq==2.1.3
Requires-Dist: gemmi==0.7.0
Requires-Dist: joblib
Requires-Dist: ml_collections
Requires-Dist: numpy
Requires-Dist: pandas
Requires-Dist: pdbeccdutils==0.8.5
Requires-Dist: posebusters==0.3.1
Requires-Dist: rdkit>=2024.09.6
Requires-Dist: scipy
Requires-Dist: tabulate
Requires-Dist: tqdm
Requires-Dist: click
Dynamic: author
Dynamic: author-email
Dynamic: license
Dynamic: license-file
Dynamic: platform
Dynamic: requires-dist
Dynamic: requires-python
Dynamic: summary
